ShiyanlouPhpJiaochengHeji20160904Fix1/README.md
ShiyanlouPhpJiaochengHeji20160904Fix1/__init__.py
ShiyanlouPhpJiaochengHeji20160904Fix1/__main__.py
ShiyanlouPhpJiaochengHeji20160904Fix1/file.epub
ShiyanlouPhpJiaochengHeji20160904Fix1/index.html
ShiyanlouPhpJiaochengHeji20160904Fix1/css/__init__.py
ShiyanlouPhpJiaochengHeji20160904Fix1/css/annotations.css
ShiyanlouPhpJiaochengHeji20160904Fix1/css/main.css
ShiyanlouPhpJiaochengHeji20160904Fix1/css/normalize.css
ShiyanlouPhpJiaochengHeji20160904Fix1/css/popup.css
ShiyanlouPhpJiaochengHeji20160904Fix1/font/__init__.py
ShiyanlouPhpJiaochengHeji20160904Fix1/font/fontello.eot
ShiyanlouPhpJiaochengHeji20160904Fix1/font/fontello.svg
ShiyanlouPhpJiaochengHeji20160904Fix1/font/fontello.ttf
ShiyanlouPhpJiaochengHeji20160904Fix1/font/fontello.woff
ShiyanlouPhpJiaochengHeji20160904Fix1/img/__init__.py
ShiyanlouPhpJiaochengHeji20160904Fix1/img/annotator-glyph-sprite.png
ShiyanlouPhpJiaochengHeji20160904Fix1/img/annotator-icon-sprite.png
ShiyanlouPhpJiaochengHeji20160904Fix1/img/apple-touch-icon.png
ShiyanlouPhpJiaochengHeji20160904Fix1/img/cancelfullscreen.png
ShiyanlouPhpJiaochengHeji20160904Fix1/img/close.png
ShiyanlouPhpJiaochengHeji20160904Fix1/img/fullscreen.png
ShiyanlouPhpJiaochengHeji20160904Fix1/img/loader.gif
ShiyanlouPhpJiaochengHeji20160904Fix1/img/menu-icon.png
ShiyanlouPhpJiaochengHeji20160904Fix1/img/save.png
ShiyanlouPhpJiaochengHeji20160904Fix1/img/saved.png
ShiyanlouPhpJiaochengHeji20160904Fix1/img/settings-s.png
ShiyanlouPhpJiaochengHeji20160904Fix1/img/settings.png
ShiyanlouPhpJiaochengHeji20160904Fix1/img/star.png
ShiyanlouPhpJiaochengHeji20160904Fix1/js/__init__.py
ShiyanlouPhpJiaochengHeji20160904Fix1/js/epub.js
ShiyanlouPhpJiaochengHeji20160904Fix1/js/epub.min.js
ShiyanlouPhpJiaochengHeji20160904Fix1/js/epub.min.map
ShiyanlouPhpJiaochengHeji20160904Fix1/js/hooks.min.js
ShiyanlouPhpJiaochengHeji20160904Fix1/js/hooks.min.map
ShiyanlouPhpJiaochengHeji20160904Fix1/js/reader.js
shiyanlou_php_jiaocheng_heji_20160904_fix1-2024.3.2.0.dist-info/METADATA
shiyanlou_php_jiaocheng_heji_20160904_fix1-2024.3.2.0.dist-info/WHEEL
shiyanlou_php_jiaocheng_heji_20160904_fix1-2024.3.2.0.dist-info/entry_points.txt
shiyanlou_php_jiaocheng_heji_20160904_fix1-2024.3.2.0.dist-info/top_level.txt
shiyanlou_php_jiaocheng_heji_20160904_fix1-2024.3.2.0.dist-info/RECORD
